proto2rapidjson/__init__.py
proto2rapidjson/__main__.py
proto2rapidjson/lexer.py
proto2rapidjson/parser.py
tests/__init__.py
tests/failedcases/__init__.py
tests/failedcases/test_badjson.py
tests/failedcases/test_badproto.py
tests/passedcases/__init__.py
tests/passedcases/test_passedcase.py
proto2rapidjson-1.1.8.dist-info/LICENSE
proto2rapidjson-1.1.8.dist-info/METADATA
proto2rapidjson-1.1.8.dist-info/WHEEL
proto2rapidjson-1.1.8.dist-info/entry_points.txt
proto2rapidjson-1.1.8.dist-info/top_level.txt
proto2rapidjson-1.1.8.dist-info/RECORD
