Metadata-Version: 2.1
Name: proto2rapidjson
Version: 1.1.8
Summary: Convert .proto file to header-only RapidJSON based c++ code
Home-page: https://github.com/Sweetnow/proto2rapidjson
Author: Jun Zhang
Author-email: zhangjun990222@gmail.com
License: UNKNOWN
Platform: UNKNOWN
Requires-Python: >=3.6
